socianAuthPySDK/__init__.py
socianAuthPySDK-0.1.8.dist-info/LICENSE.txt
socianAuthPySDK-0.1.8.dist-info/METADATA
socianAuthPySDK-0.1.8.dist-info/WHEEL
socianAuthPySDK-0.1.8.dist-info/top_level.txt
socianAuthPySDK-0.1.8.dist-info/RECORD
