Metadata-Version: 2.1
Name: socianAuthPySDK
Version: 0.1.8
Summary: socianAuthPySDK test publish.
Home-page: UNKNOWN
Author: socian
Author-email: contact@socian.ai
License: MIT
Platform: UNKNOWN
Requires-Dist: requests (>=2.27.1)
